gitleak/__init__.py
gitleak/installer.py
trufflehog/__init__.py
trufflehog/trufflehog.py
zap/__init__.py
zap/zap.py
security_packages-1.0.dist-info/METADATA
security_packages-1.0.dist-info/WHEEL
security_packages-1.0.dist-info/entry_points.txt
security_packages-1.0.dist-info/top_level.txt
security_packages-1.0.dist-info/RECORD
