Metadata-Version: 2.1
Name: security_packages
Version: 1.0
Summary: A merged package combining gitleaks, trufflehhog and zap
Classifier: Programming Language :: Python :: 3
Classifier: License :: OSI Approved :: MIT License
Classifier: Operating System :: OS Independent
Requires-Python: >=3.6
Requires-Dist: requests >=2.25.1
